promsoft_pecom_interface/__init__.py
promsoft_pecom_interface/cargopickup.py
promsoft_pecom_interface/common.py
promsoft_pecom_interface/preregistration.py
promsoft_pecom_interface-0.1.4.dist-info/METADATA
promsoft_pecom_interface-0.1.4.dist-info/WHEEL
promsoft_pecom_interface-0.1.4.dist-info/RECORD
