Metadata-Version: 2.1
Name: promsoft-pecom-interface
Version: 0.1.4
Summary: Интерфейс HTTP API для транспортной компании PECOM 
Author: Promsoft
Author-email: info@promsoft.ru
Requires-Python: >=3.10,<4.0
Classifier: Programming Language :: Python :: 3
Classifier: Programming Language :: Python :: 3.10
Classifier: Programming Language :: Python :: 3.11
Requires-Dist: pydantic (>=1.10.7,<2.0.0)
